apt_mirror/__init__.py
apt_mirror/__main__.py
apt_mirror/aiofile.py
apt_mirror/apt_mirror.py
apt_mirror/config.py
apt_mirror/filter.py
apt_mirror/logs.py
apt_mirror/netrc.py
apt_mirror/prometheus.py
apt_mirror/repository.py
apt_mirror/uvloop.py
apt_mirror/version.py
apt_mirror/download/__init__.py
apt_mirror/download/download_file.py
apt_mirror/download/downloader.py
apt_mirror/download/factory.py
apt_mirror/download/format.py
apt_mirror/download/proxy.py
apt_mirror/download/response.py
apt_mirror/download/slow_rate_protector.py
apt_mirror/download/url.py
apt_mirror/download/protocols/__init__.py
apt_mirror/download/protocols/ftp.py
apt_mirror/download/protocols/http.py
apt_mirror-15.dist-info/licenses/LICENSE
apt_mirror-15.dist-info/METADATA
apt_mirror-15.dist-info/WHEEL
apt_mirror-15.dist-info/entry_points.txt
apt_mirror-15.dist-info/top_level.txt
apt_mirror-15.dist-info/RECORD
