Metadata-Version: 2.4
Name: apt-mirror
Version: 15
Summary: apt-mirror Python reimplementation
Author-email: Yuri Konotopov <ykonotopov@gnome.org>
License:                     GNU GENERAL PUBLIC LICENSE
Project-URL: Homepage, https://gitlab.com/apt-mirror2/apt-mirror2/
Project-URL: Repository, https://gitlab.com/apt-mirror2/apt-mirror2.git
Project-URL: Github, https://github.com/nE0sIghT/apt-mirror2.git
Project-URL: Issues, https://gitlab.com/apt-mirror2/apt-mirror2/-/issues
Project-URL: Changelog, https://gitlab.com/apt-mirror2/apt-mirror2/-/commits/master/
Keywords: apt,debian
Classifier: Programming Language :: Python :: 3
Classifier: Framework :: AsyncIO
Classifier: License :: OSI Approved :: GNU General Public License v3 or later (GPLv3+)
Classifier: Operating System :: POSIX :: Linux
Requires-Python: >=3.10
License-File: LICENSE
Requires-Dist: aiofile==3.9.0
Requires-Dist: aiolimiter==1.1.0
Requires-Dist: aioftp==0.23.1
Requires-Dist: httpx[http2]==0.27.2
Requires-Dist: python-debian==0.1.49
Provides-Extra: dev
Requires-Dist: pip-tools==7.4.1; extra == "dev"
Requires-Dist: pyinstaller==6.11.0; extra == "dev"
Requires-Dist: pylint==3.3.1; extra == "dev"
Requires-Dist: pytest==9.0.2; extra == "dev"
Requires-Dist: ruff==0.7.4; extra == "dev"
Provides-Extra: aiofiles
Requires-Dist: aiofiles==24.1.0; extra == "aiofiles"
Provides-Extra: prometheus
Requires-Dist: prometheus-client==0.20.0; extra == "prometheus"
Provides-Extra: uvloop
Requires-Dist: uvloop==0.21.0; extra == "uvloop"
Dynamic: license-file
